nodestream_plugin_neptune/__init__.py
nodestream_plugin_neptune/extractor.py
nodestream_plugin_neptune/ingest_query_builder.py
nodestream_plugin_neptune/neptune_connection.py
nodestream_plugin_neptune/neptune_connector.py
nodestream_plugin_neptune/neptune_migrator.py
nodestream_plugin_neptune/neptune_query_executor.py
nodestream_plugin_neptune/query.py
nodestream_plugin_neptune/type_retriever.py
nodestream_plugin_neptune-0.14.0.dist-info/METADATA
nodestream_plugin_neptune-0.14.0.dist-info/WHEEL
nodestream_plugin_neptune-0.14.0.dist-info/entry_points.txt
nodestream_plugin_neptune-0.14.0.dist-info/RECORD
