Metadata-Version: 2.3
Name: nodestream-plugin-neptune
Version: 0.14.0
Summary: 
Author: Zach Probst
Author-email: Zach_Probst@intuit.com
Requires-Python: >=3.10,<4.0
Classifier: Programming Language :: Python :: 3
Classifier: Programming Language :: Python :: 3.10
Classifier: Programming Language :: Python :: 3.11
Classifier: Programming Language :: Python :: 3.12
Classifier: Programming Language :: Python :: 3.13
Requires-Dist: aiobotocore (>=2.12.0,<3.0.0)
Requires-Dist: botocore (>=1.34.40)
Requires-Dist: cymple (>=0.11.0,<0.12.0)
Requires-Dist: nodestream (>=0.14.0,<0.15.0)
